{
  "currently": {
    "summary": "Mostly Cloudy",
    "precipProbability": 0,
    "visibility": 5.56,
    "windGust": 4.3,
    "precipIntensity": 0,
    "icon": "partly-cloudy-night",
    "cloudCover": 0.83,
    "windBearing": 164,
    "apparentTemperature": 50.4,
    "pressure": 1023.72,
    "dewPoint": 46.38,
    "ozone": 290.5,
    "nearestStormBearing": 129,
    "nearestStormDistance": 20,
    "temperature": 50.4,
    "humidity": 0.86,
    "time": 1508135982,
    "windSpeed": 1.97,
    "uvIndex": 0
  },
  "offset": -7,
  "timezone": "America/Los_Angeles",
  "latitude": 48.962982,
  "daily": {
    "summary": "Rain tomorrow through next Sunday, with temperatures falling to 53°F on Friday.",
    "data": [
      {
        "windGust": 5.76,
        "apparentTemperatureMinTime": 1508079600,
        "temperatureMax": 60.66,
        "icon": "partly-cloudy-night",
        "precipIntensityMax": 1.0E-4,
        "windBearing": 7,
        "ozone": 291.01,
        "temperatureMaxTime": 1508104800,
        "apparentTemperatureMin": 44.5,
        "sunsetTime": 1508116880,
        "temperatureLow": 48.97,
        "humidity": 0.81,
        "moonPhase": 0.87,
        "windSpeed": 0.59,
        "apparentTemperatureLowTime": 1508148000,
        "sunriseTime": 1508077918,
        "apparentTemperatureLow": 48.09,
        "summary": "Mostly cloudy starting in the evening.",
        "precipProbability": 0,
        "temperatureHighTime": 1508104800,
        "visibility": 5.43,
        "precipIntensity": 0,
        "cloudCover": 0.4,
        "temperatureMin": 44.5,
        "apparentTemperatureHighTime": 1508104800,
        "pressure": 1027.01,
        "dewPoint": 45.77,
        "temperatureMinTime": 1508079600,
        "uvIndexTime": 1508090400,
        "apparentTemperatureMax": 60.66,
        "temperatureHigh": 60.66,
        "temperatureLowTime": 1508148000,
        "apparentTemperatureHigh": 60.66,
        "time": 1508050800,
        "precipIntensityMaxTime": 1508065200,
        "windGustTime": 1508090400,
        "uvIndex": 2,
        "apparentTemperatureMaxTime": 1508104800
      },
      {
        "windGust": 27.38,
        "apparentTemperatureMinTime": 1508148000,
        "temperatureMax": 53.71,
        "icon": "rain",
        "precipIntensityMax": 0.0874,
        "windBearing": 144,
        "ozone": 281.4,
        "temperatureMaxTime": 1508187600,
        "apparentTemperatureMin": 48.09,
        "sunsetTime": 1508203162,
        "temperatureLow": 51.71,
        "precipType": "rain",
        "humidity": 0.84,
        "moonPhase": 0.9,
        "windSpeed": 4.74,
        "apparentTemperatureLowTime": 1508252400,
        "sunriseTime": 1508164410,
        "apparentTemperatureLow": 51.71,
        "summary": "Rain throughout the day.",
        "precipProbability": 0.93,
        "temperatureHighTime": 1508187600,
        "visibility": 10,
        "precipIntensity": 0.0304,
        "cloudCover": 0.95,
        "temperatureMin": 48.97,
        "apparentTemperatureHighTime": 1508187600,
        "pressure": 1019.6,
        "dewPoint": 47.02,
        "temperatureMinTime": 1508148000,
        "uvIndexTime": 1508173200,
        "apparentTemperatureMax": 53.71,
        "temperatureHigh": 53.71,
        "temperatureLowTime": 1508252400,
        "apparentTemperatureHigh": 53.71,
        "time": 1508137200,
        "precipIntensityMaxTime": 1508198400,
        "windGustTime": 1508220000,
        "uvIndex": 1,
        "apparentTemperatureMaxTime": 1508187600
      },
      {
        "windGust": 34.35,
        "apparentTemperatureMinTime": 1508306400,
        "temperatureMax": 56.51,
        "icon": "rain",
        "precipIntensityMax": 0.151,
        "windBearing": 199,
        "ozone": 294.97,
        "temperatureMaxTime": 1508274000,
        "apparentTemperatureMin": 41.72,
        "sunsetTime": 1508289445,
        "temperatureLow": 43.46,
        "precipType": "rain",
        "humidity": 0.82,
        "moonPhase": 0.94,
        "windSpeed": 7.52,
        "apparentTemperatureLowTime": 1508310000,
        "sunriseTime": 1508250902,
        "apparentTemperatureLow": 40.97,
        "summary": "Rain until afternoon, starting again overnight.",
        "precipProbability": 0.98,
        "temperatureHighTime": 1508274000,
        "visibility": 10,
        "precipIntensity": 0.0476,
        "cloudCover": 0.84,
        "temperatureMin": 44.02,
        "apparentTemperatureHighTime": 1508274000,
        "pressure": 1013.61,
        "dewPoint": 46.05,
        "temperatureMinTime": 1508306400,
        "uvIndexTime": 1508259600,
        "apparentTemperatureMax": 56.51,
        "temperatureHigh": 56.51,
        "temperatureLowTime": 1508310000,
        "apparentTemperatureHigh": 56.51,
        "time": 1508223600,
        "precipIntensityMaxTime": 1508241600,
        "windGustTime": 1508234400,
        "uvIndex": 1,
        "apparentTemperatureMaxTime": 1508274000
      },
      {
        "windGust": 30.16,
        "apparentTemperatureMinTime": 1508310000,
        "temperatureMax": 56.04,
        "icon": "rain",
        "precipIntensityMax": 0.1371,
        "windBearing": 154,
        "ozone": 280.29,
        "temperatureMaxTime": 1508367600,
        "apparentTemperatureMin": 40.97,
        "sunsetTime": 1508375729,
        "temperatureLow": 52.02,
        "precipType": "rain",
        "humidity": 0.85,
        "moonPhase": 0.97,
        "windSpeed": 9.63,
        "apparentTemperatureLowTime": 1508425200,
        "sunriseTime": 1508337395,
        "apparentTemperatureLow": 52.02,
        "summary": "Rain throughout the day.",
        "precipProbability": 0.99,
        "temperatureHighTime": 1508367600,
        "visibility": 7.32,
        "precipIntensity": 0.0867,
        "cloudCover": 0.98,
        "temperatureMin": 43.46,
        "apparentTemperatureHighTime": 1508367600,
        "pressure": 1005.18,
        "dewPoint": 46.97,
        "temperatureMinTime": 1508310000,
        "uvIndexTime": 1508346000,
        "apparentTemperatureMax": 56.04,
        "temperatureHigh": 56.04,
        "temperatureLowTime": 1508425200,
        "apparentTemperatureHigh": 56.04,
        "time": 1508310000,
        "precipIntensityMaxTime": 1508367600,
        "windGustTime": 1508342400,
        "uvIndex": 1,
        "apparentTemperatureMaxTime": 1508367600
      },
      {
        "windGust": 23.63,
        "apparentTemperatureMinTime": 1508472000,
        "temperatureMax": 52.93,
        "icon": "rain",
        "precipIntensityMax": 0.0884,
        "windBearing": 183,
        "ozone": 295.84,
        "temperatureMaxTime": 1508400000,
        "apparentTemperatureMin": 47.49,
        "sunsetTime": 1508462014,
        "temperatureLow": 45.79,
        "precipType": "rain",
        "humidity": 0.93,
        "moonPhase": 0.01,
        "windSpeed": 6.67,
        "apparentTemperatureLowTime": 1508508000,
        "sunriseTime": 1508423888,
        "apparentTemperatureLow": 44.33,
        "summary": "Rain throughout the day.",
        "precipProbability": 0.98,
        "temperatureHighTime": 1508421600,
        "precipIntensity": 0.0718,
        "cloudCover": 1,
        "temperatureMin": 48.91,
        "apparentTemperatureHighTime": 1508421600,
        "pressure": 997.93,
        "dewPoint": 49.48,
        "temperatureMinTime": 1508479200,
        "uvIndexTime": 1508432400,
        "apparentTemperatureMax": 52.93,
        "temperatureHigh": 52.3,
        "temperatureLowTime": 1508508000,
        "apparentTemperatureHigh": 52.3,
        "time": 1508396400,
        "precipIntensityMaxTime": 1508464800,
        "windGustTime": 1508403600,
        "uvIndex": 1,
        "apparentTemperatureMaxTime": 1508400000
      },
      {
        "windGust": 20.03,
        "apparentTemperatureMinTime": 1508551200,
        "temperatureMax": 52.56,
        "icon": "rain",
        "precipIntensityMax": 0.042,
        "windBearing": 169,
        "ozone": 335,
        "temperatureMaxTime": 1508533200,
        "apparentTemperatureMin": 43.24,
        "sunsetTime": 1508548301,
        "temperatureLow": 44.1,
        "precipType": "rain",
        "humidity": 0.89,
        "moonPhase": 0.04,
        "windSpeed": 4.23,
        "apparentTemperatureLowTime": 1508598000,
        "sunriseTime": 1508510382,
        "apparentTemperatureLow": 40.58,
        "summary": "Light rain throughout the day.",
        "precipProbability": 0.86,
        "temperatureHighTime": 1508533200,
        "precipIntensity": 0.0272,
        "cloudCover": 0.86,
        "temperatureMin": 45.42,
        "apparentTemperatureHighTime": 1508533200,
        "pressure": 1005.2,
        "dewPoint": 45.18,
        "temperatureMinTime": 1508551200,
        "uvIndexTime": 1508518800,
        "apparentTemperatureMax": 52.56,
        "temperatureHigh": 52.56,
        "temperatureLowTime": 1508598000,
        "apparentTemperatureHigh": 52.56,
        "time": 1508482800,
        "precipIntensityMaxTime": 1508482800,
        "windGustTime": 1508551200,
        "uvIndex": 1,
        "apparentTemperatureMaxTime": 1508533200
      },
      {
        "windGust": 12.77,
        "apparentTemperatureMinTime": 1508598000,
        "temperatureMax": 52.81,
        "icon": "rain",
        "precipIntensityMax": 0.1217,
        "windBearing": 123,
        "ozone": 299.85,
        "temperatureMaxTime": 1508619600,
        "apparentTemperatureMin": 40.58,
        "sunsetTime": 1508634588,
        "temperatureLow": 50.73,
        "precipType": "rain",
        "humidity": 0.84,
        "moonPhase": 0.07,
        "windSpeed": 5.43,
        "apparentTemperatureLowTime": 1508637600,
        "sunriseTime": 1508596876,
        "apparentTemperatureLow": 50.73,
        "summary": "Rain throughout the day.",
        "precipProbability": 0.85,
        "temperatureHighTime": 1508619600,
        "precipIntensity": 0.0637,
        "cloudCover": 0.52,
        "temperatureMin": 44.1,
        "apparentTemperatureHighTime": 1508619600,
        "pressure": 1013.87,
        "dewPoint": 45.06,
        "temperatureMinTime": 1508598000,
        "uvIndexTime": 1508601600,
        "apparentTemperatureMax": 52.81,
        "temperatureHigh": 52.81,
        "temperatureLowTime": 1508637600,
        "apparentTemperatureHigh": 52.81,
        "time": 1508569200,
        "precipIntensityMaxTime": 1508626800,
        "windGustTime": 1508652000,
        "uvIndex": 1,
        "apparentTemperatureMaxTime": 1508619600
      },
      {
        "windGust": 23,
        "apparentTemperatureMinTime": 1508655600,
        "temperatureMax": 58.42,
        "icon": "rain",
        "precipIntensityMax": 0.1384,
        "windBearing": 157,
        "ozone": 265.5,
        "temperatureMaxTime": 1508709600,
        "apparentTemperatureMin": 52.68,
        "sunsetTime": 1508720876,
        "temperatureLow": 51.48,
        "precipType": "rain",
        "humidity": 0.93,
        "moonPhase": 0.1,
        "windSpeed": 6.46,
        "apparentTemperatureLowTime": 1508770800,
        "sunriseTime": 1508683370,
        "apparentTemperatureLow": 51.48,
        "summary": "Rain throughout the day.",
        "precipProbability": 0.87,
        "temperatureHighTime": 1508709600,
        "precipIntensity": 0.0797,
        "cloudCover": 1,
        "temperatureMin": 52.68,
        "apparentTemperatureHighTime": 1508709600,
        "pressure": 1018.1,
        "dewPoint": 53.97,
        "temperatureMinTime": 1508655600,
        "uvIndexTime": 1508691600,
        "apparentTemperatureMax": 58.42,
        "temperatureHigh": 58.42,
        "temperatureLowTime": 1508770800,
        "apparentTemperatureHigh": 58.42,
        "time": 1508655600,
        "precipIntensityMaxTime": 1508673600,
        "windGustTime": 1508698800,
        "uvIndex": 1,
        "apparentTemperatureMaxTime": 1508709600
      }
    ],
    "icon": "rain"
  },
  "longitude": -122.458015
}